{
    "name": "doYouSeeMe",
    "ptname": "voceMeVe",
    "syntax": {
        "c": "int doYouSeeMe ( void );",
        "python": "doYouSeeMe()",
        "blocks": "Inimigo me enxerga?"
    },
    "description": {
        "long": "Verifica se o alvo selecionado está enxergando o gladiador. O alvo enxerga o gladiador caso o gladiador esteja dentro do campo de visão dele.",
        "brief": "Descobre se o alvo enxerga o gladiador."
    },
    "param": {
        "default": [
            {"name": "void", "description": "A função não recebe parâmetros."}
        ]
    },
    "treturn": {
        "default": "Retorna True caso o gladiador esteja no campo de visão do alvo selecionado. Caso não esteja, ou o alvo selecionado não esteja no campo de visão do gladiador, retorna False.",
        "c": "Retorna 1 caso o gladiador esteja no campo de visão do alvo selecionado. Caso não esteja, ou o alvo selecionado não esteja no campo de visão do gladiador, retorna 0."
    },
    "sample": {
        "c": "1.c",
        "python": "1.py",
            "blocks": "1.xml"
    },
    "explain": "No exemplo o gladiador verifica se o alvo está visível e caso não esteja procura um novo alvo com menos pontos de vida em seu campo de visão. Caso ainda esteja visível verifica se o alvo enxerga o gladiador e se move de maneira a ficar olhando para as costas do alvo. Quando isso acontecer, o gladiador ataca o alvo.",
    "seealso": [
        "getLowHp",
        "attackRanged",
        "getTargetX",
        "getTargetY",
        "isTargetVisible",
        "stepLeft",
        "turnToTarget"
    ],
    "snippet": {
        "c": "int ${1:seen} = doYouSeeMe();",
        "python": "${1:seen} = doYouSeeMe()"
    }
}
